steam_monitor.py
steam_monitor-1.6.dist-info/licenses/LICENSE
steam_monitor-1.6.dist-info/METADATA
steam_monitor-1.6.dist-info/WHEEL
steam_monitor-1.6.dist-info/entry_points.txt
steam_monitor-1.6.dist-info/top_level.txt
steam_monitor-1.6.dist-info/RECORD
