Metadata-Version: 2.4
Name: steam_monitor
Version: 1.6
Summary: Tool implementing real-time tracking of Steam players activities
Author-email: Michal Szymanski <misiektoja-pypi@rm-rf.ninja>
License-Expression: GPL-3.0-or-later
Project-URL: Homepage, https://github.com/misiektoja/steam_monitor
Project-URL: Source, https://github.com/misiektoja/steam_monitor
Project-URL: Changelog, https://github.com/misiektoja/steam_monitor/blob/main/RELEASE_NOTES.md
Keywords: steam,monitoring,tracking,real-time,osint
Classifier: Programming Language :: Python :: 3
Classifier: Operating System :: OS Independent
Classifier: Operating System :: Microsoft :: Windows
Classifier: Operating System :: POSIX :: Linux
Classifier: Operating System :: MacOS :: MacOS X
Requires-Python: >=3.6
License-File: LICENSE
Requires-Dist: steam[client]>=1.4.3
Requires-Dist: requests>=2.0
Requires-Dist: python-dateutil>=2.8
Requires-Dist: python-dotenv>=0.19
Requires-Dist: colorama>=0.4.6; platform_system == "Windows"
Dynamic: license-file
